main.py
cm_docs_mcp_server-1.0.0.dist-info/METADATA
cm_docs_mcp_server-1.0.0.dist-info/WHEEL
cm_docs_mcp_server-1.0.0.dist-info/entry_points.txt
cm_docs_mcp_server-1.0.0.dist-info/RECORD
