Metadata-Version: 2.4
Name: cm-docs-mcp-server
Version: 1.0.0
Summary: MCP server for CM.com documentation
Author: CM.com
Keywords: cm.com,documentation,mcp
Requires-Python: >=3.10
Requires-Dist: beautifulsoup4>=4.12.0
Requires-Dist: httpx>=0.27.0
Requires-Dist: lxml>=5.0.0
Requires-Dist: mcp>=1.23.0
